{
	"configurations" : 
	[
		{
			"directories" : 
			[
				{
					"build" : ".",
					"jsonFile" : "directory-.-Debug-f5ebdc15457944623624.json",
					"minimumCMakeVersion" : 
					{
						"string" : "3.17"
					},
					"projectIndex" : 0,
					"source" : ".",
					"targetIndexes" : 
					[
						0
					]
				}
			],
			"name" : "Debug",
			"projects" : 
			[
				{
					"directoryIndexes" : 
					[
						0
					],
					"name" : "Exercice6",
					"targetIndexes" : 
					[
						0
					]
				}
			],
			"targets" : 
			[
				{
					"directoryIndex" : 0,
					"id" : "Exercice6::@6890427a1f51a3e7e1df",
					"jsonFile" : "target-Exercice6-Debug-068730ed0dde717a3e35.json",
					"name" : "Exercice6",
					"projectIndex" : 0
				}
			]
		}
	],
	"kind" : "codemodel",
	"paths" : 
	{
		"build" : "/home/ayoub/CLionProjects/Exercice6/cmake-build-debug",
		"source" : "/home/ayoub/CLionProjects/Exercice6"
	},
	"version" : 
	{
		"major" : 2,
		"minor" : 5
	}
}
